<Orders>
  <Order>
    <ID>XML-1</ID>
    <SKU>LSR-MARK-03</SKU>
    <Custom>Name: New, Color: Silver, Image: Hearth</Custom>
    <Buyer>Angela</Buyer>
  </Order>
  <Order>
    <ID>XML-2</ID>
    <SKU>LSR-MARK-03</SKU>
    <Custom>Name: New, Color: Silver, Image: Hearth</Custom>
    <Buyer>Angela</Buyer>
  </Order>
  <Order>
    <ID>XML-3</ID>
    <SKU>LSR-MARK-03</SKU>
    <Custom>Name: New, Color: Silver, Image: Hearth</Custom>
    <Buyer>Angela</Buyer>
  </Order>
  <Order>
    <ID>XML-4</ID>
    <SKU>LSR-MARK-04</SKU>
    <Custom>Name: New, Color: Silver, Image: Hearth</Custom>
    <Buyer>Angela</Buyer>
  </Order>
</Orders>
